{
  "package": {
    "name": "OpenSpecy",
    "version": "1.7.1",
    "source": "local::.",
    "commit": "3406dcdedfae1f321c48c5da2243e9032a8c4b57"
  },
  "wasm_repo": {
    "url": "https://wincowgerDEV.github.io/OpenSpecy-package/wasm/3406dcdedfae1f321c48c5da2243e9032a8c4b57/repo",
    "immutable": true
  },
  "app": {
    "source": "inst/shiny",
    "wasm_mode": true,
    "library_types": ["medoid_derivative", "medoid_nobaseline", "model_derivative", "model_nobaseline"]
  },
  "package_roots": ["local::.", "shiny", "shinyjs", "shinyWidgets", "bs4Dash", "dplyr", "DT", "ggplot2", "reshape2", "plotly", "curl", "scales", "caTools", "data.table", "jsonlite", "hyperSpec", "mmand", "digest", "glmnet", "jpeg", "hdf5r", "matrixStats"],
  "package_names": ["OpenSpecy", "shiny", "shinyjs", "shinyWidgets", "bs4Dash", "dplyr", "DT", "ggplot2", "reshape2", "plotly", "curl", "scales", "caTools", "data.table", "jsonlite", "hyperSpec", "mmand", "digest", "glmnet", "jpeg", "hdf5r", "matrixStats"],
  "generated_at": "2026-07-14T12:19:01Z"
}
